wiki/__init__.py
wiki/cli.py
wiki/main.py
wiki/sql2csv.py
wikiext/__init__.py
wikiext/main.py
wikiext/utility/__init__.py
wikiext/utility/sql2csv.py
wikiext-0.0.12.dist-info/LICENSE
wikiext-0.0.12.dist-info/METADATA
wikiext-0.0.12.dist-info/WHEEL
wikiext-0.0.12.dist-info/entry_points.txt
wikiext-0.0.12.dist-info/top_level.txt
wikiext-0.0.12.dist-info/RECORD
