Metadata-Version: 2.1
Name: wikiext
Version: 0.0.12
Summary: Wiki Extractor 
Home-page: https://github.com/voidful/WikiExtractor
Author: Voidful
Author-email: voidful.stack@gmail.com
License: Apache
Keywords: wikiext wikiextactor extractor
Platform: UNKNOWN
Classifier: Development Status :: 4 - Beta
Classifier: Intended Audience :: Science/Research
Classifier: Topic :: Scientific/Engineering :: Artificial Intelligence
Classifier: License :: OSI Approved :: Apache Software License
Classifier: Programming Language :: Python :: 3.5
Requires-Python: >=3.0
License-File: LICENSE
Requires-Dist: gensim
Requires-Dist: tqdm
Requires-Dist: nlp2
Requires-Dist: bz2file
Requires-Dist: opencc-python-reimplemented
